danktool/__init__.py
danktool/ctypes.py
danktool/datetime.py
danktool/multithread.py
danktool/pillow.py
danktool/requests.py
danktool/terminal.py
danktool/text.py
danktool/tkinter.py
danktool/traceback.py
danktool/winreg.py
danktool-0.0.1.dist-info/METADATA
danktool-0.0.1.dist-info/WHEEL
danktool-0.0.1.dist-info/top_level.txt
danktool-0.0.1.dist-info/RECORD
